pytest_runtime_xfail.py
pytest_runtime_xfail-1.1.1.dist-info/METADATA
pytest_runtime_xfail-1.1.1.dist-info/WHEEL
pytest_runtime_xfail-1.1.1.dist-info/entry_points.txt
pytest_runtime_xfail-1.1.1.dist-info/licenses/LICENSE.txt
pytest_runtime_xfail-1.1.1.dist-info/RECORD
