Metadata-Version: 2.4
Name: pytest-runtime-xfail
Version: 1.1.1
Summary: Call runtime_xfail() to mark running test as xfail.
Project-URL: Home, https://github.com/okken/pytest-runtime-xfail
Author: Brian Okken
License: MIT License
License-File: LICENSE.txt
Classifier: Development Status :: 5 - Production/Stable
Classifier: Framework :: Pytest
Classifier: Intended Audience :: Developers
Classifier: Programming Language :: Python
Classifier: Programming Language :: Python :: 3.8
Classifier: Programming Language :: Python :: 3.9
Classifier: Programming Language :: Python :: 3.10
Classifier: Programming Language :: Python :: 3.11
Classifier: Programming Language :: Python :: 3.12
Classifier: Programming Language :: Python :: 3.13
Classifier: Programming Language :: Python :: 3.14
Classifier: Topic :: Software Development :: Testing
Classifier: Topic :: Utilities
Requires-Python: >=3.8
Requires-Dist: pytest>=5.0.0
Provides-Extra: dev
Requires-Dist: build; extra == 'dev'
Requires-Dist: tox; extra == 'dev'
Requires-Dist: tox-uv; extra == 'dev'
